ipbase/__init__.py
ipbase/client.py
ipbase-0.1.dist-info/METADATA
ipbase-0.1.dist-info/WHEEL
ipbase-0.1.dist-info/top_level.txt
ipbase-0.1.dist-info/RECORD
